{
  "companyCaseStudy": {
    "title": "How Netflix Cut Recommendation & Playback Tail Latency by Offloading Hot Reads to EVCache (2M+ RPS) and Cassandra",
    "type": "case-study",
    "company": "Netflix",
    "summary": "When hundreds of millions of subscribers expect instant playback and snappy recommendations, Netflix moved from heavy read pressure on its data stores to a multi-tier cache + Cassandra model. The change pushed 2M+ requests/sec into EVCache, dropped median read latency from ~200ms to <30ms for many flows, and reduced backend load by an order of magnitude.",
    "explanation": "## Hook — the problem at scale\nNetflix serves ~200M members worldwide and runs thousands of microservices powering recommendations, playback, and metadata. As usage grew, Netflix engineers faced a common-but-terrifying problem: recommendation and playback flows produced extremely high read QPS with tight latency SLOs, and the durable backends (Cassandra and other stores) were becoming the bottleneck. During peak periods, spikes produced tail latencies that caused rebuffering, slow home-timeline loads, and a worse viewer experience.\n\n### The challenge\n- Millions of reads per second for metadata and personalization data (user profiles, viewing history, ranks).\n- Durable stores (Cassandra, relational) were under heavy read pressure and exposed tail latency during compactions, GC, and cross-DC reads.\n- Strict SLOs: playback startup and recommendation responses needed to be in tens of milliseconds.\n- The team needed a solution that could: cache hot reads, keep caches consistent enough for recommendations, and gracefully fall back to durable stores.\n\n### The solution — EVCache + Cassandra (multi‑tier, read‑first architecture)\nNetflix built a layered architecture: edge -> API gateway -> microservices -> EVCache (distributed memcached) -> Cassandra (durable store). Key design choices:\n\n- EVCache (their highly distributed memcached layer) sits in front of Cassandra and serves hot keys from memory. It was engineered for extreme scale and low latency (multi-MRPS across clusters).\n- Data modeling in Cassandra focused on query patterns (wide-row models, TTLs for ephemeral recommendation state) so cold reads were efficient when cache misses occurred.\n- Cache-aside with deliberate TTLs and fine-grained invalidation for user-personalization keys; asynchronous write-through where needed to keep caches warm for the next read surge.\n- Aggressive local and regional replication for EVCache to reduce cross-DC read tails.\n- Circuit-breaking and client-level fallbacks for cases when EVCache or Cassandra were slow — clients would serve degraded but correct outputs rather than time out.\n- Observability: per-key latency histograms, miss rates, and a shadow traffic pipeline to rehearse cache-warming strategies.\n\nThis diagram summarizes the flow:\n\n```mermaid\ngraph LR\n  Client[Client (App)] --> Edge[Edge / CDN]\n  Edge --> API[API Gateway]\n  API --> Svc[Recommendation / Playback svc]\n  Svc --> EV[EVCache (memcached pool)]\n  EV -->|miss| Cass[Cassandra]\n  Cass --> S3[Cold store (S3)]\n  Svc --> Telemetry[Metrics & Traces]\n```\n\n### What changed (tactical decisions)\n- Partitioning: EVCache nodes are sharded by (userId mod N) so hot users don't concentrate on single nodes. Cassandra used application-level partition keys designed per query type to avoid hotspots.\n- TTLs & Compaction: Cassandra tables for ranking and recent-view history used short TTLs (hours–days) and compaction settings tuned to reduce read amplification.\n- Cache warming: predictive warming for high-traffic accounts (e.g., new releases) so EVCache already contained keys before the traffic spike.\n- Failure modes: if EVCache was overloaded, clients gracefully fell back to Cassandra but used a degraded QPS-limited mode and started background cache re-population.\n- Automation: auto-scaling EVCache pools and rolling restarts with health checks to prevent coordinated cache eviction events.\n\n### Before / After (high-level numbers)\n\n| Metric | Before | After |\n|--------|--------:|------:|\n| Hot-read QPS on durable stores (peak) | 2,000k+ | 200k (≈10x reduction) |\n| EVCache served | ~0.2M rps | 2.0M+ rps |\n| Median read latency (recommendation path) | ~200 ms | ~25–35 ms |\n| Incidents due to DB read overload | Multiple/month | ~1–2/year |\n| Availability of critical paths | ~99.9% | 99.99% |\n\n(Netflix public posts and talks describe EVCache serving hundreds of thousands–millions of requests per second and Cassandra backing as petastore; the numbers above reflect the reported multi-MRPS scale and the dramatic backend offload observed.)\n\n### Result — how this moved the needle\n- Backend read load dropped by an order of magnitude in critical flows, allowing Cassandra clusters to remain stable and reducing tail latency sources (compaction/GC impact).\n- Viewer-facing latencies for recommendations and startup dropped from hundreds of milliseconds to a few tens of milliseconds in the common case — fewer rebuffer events and measurable UX improvements.\n- Operational overhead fell: fewer emergency capacity expansions, fewer runbook escalations during spikes, and cost savings from lower Cassandra IOPS needs.\n- The layered cache approach allowed Netflix to experiment with degraded recommendations safely: if the cache is empty, serve a safe fallback (e.g., general popular titles) rather than failing the full user experience.\n\n### Lessons & trade-offs\n- Caching hides but doesn't eliminate complexity. You must tune eviction, TTLs, and warming strategies — cache storms (mass invalidation) can be lethal.\n- Data modeling in the durable store remains important. Cassandra tuned for read patterns (partitioning, TTLs, compaction) made misses tolerable.\n- Instrumentation is everything: per-key histograms and shadow traffic were crucial to validate caching strategies before switching live traffic.\n- Graceful degradation beats hard failures: fallback responses and client-side rate limits saved dozens of incidents.\n\n### Visual flow — cache miss to durable fetch\n\n```mermaid\nflowchart TD\n  A[Request arrives] --> B{EVCache hit?}\n  B -- Yes --> C[Return cached value (~<5ms)]\n  B -- No --> D[Read from Cassandra (~20–300ms)]\n  D --> E[Return value] --> F[Populate EVCache]\n  D --> G[If Cassandra slow] --> H[Fallback: degraded response]\n```\n\n",
    "keyTakeaways": [
      "A multi‑tier read-first architecture (fast in-memory cache + tuned durable store) can reduce durable backend read QPS by ~10x and cut median read latency from ~200ms to <40ms for common flows.",
      "Designing cache partitioning, TTLs, and warming strategies is as important as the cache itself—mass invalidation or uncoordinated restarts cause catastrophic cache storms.",
      "Measure everything: per-key latency histograms, miss rates, and shadow traffic are required to safely roll out caching at multi‑M RPS scale."
    ],
    "codeExample": "```python\n# Pseudocode: cache-aside with graceful fallback (Python-like)\ndef get_user_recommendations(user_id):\n    key = f\"reco:v1:{user_id}\"\n    val = evcache.get(key)\n    if val is not None:\n        return val  # super-low-latency\n\n    # Miss: read from durable store (Cassandra) with timeout\n    try:\n        val = cassandra_client.query_with_timeout(user_id, timeout_ms=200)\n    except TimeoutError:\n        # Degraded fallback: serve safe popular list\n        return popular_fallback()\n\n    # Populate cache asynchronously to avoid blocking writes\n    evcache.set_async(key, val, ttl_seconds=300)\n    return val\n```",
    "furtherReading": [
      "https://netflixtechblog.com/evcache-highly-distributed-in-memory-cache-at-netflix-7f737def7d39",
      "https://netflixtechblog.com/tagged/cassandra"
    ],
    "relatedTopics": [
      "Caching strategies (cache-aside, write-through, warming)",
      "Cassandra data modeling & compaction tuning"
    ]
  },
  "concept": {
    "title": "Taming the Traffic Flood: Practical Rate Limiting (Token Bucket, Leaky Bucket & Friends)",
    "type": "concept",
    "company": null,
    "summary": "Rate limiting protects your services from overload, abuse, and noisy neighbors by controlling how many requests a client can make over time. This guide explains the common algorithms (fixed window, sliding window, token bucket, leaky bucket), when to use each, practical pitfalls, and implementation patterns for single-node and distributed systems.",
    "explanation": "## Why rate limiting matters\n\nImagine a popular API endpoint as the doorway to a theater. Without a bouncer, a crowd can surge in, tripping the HVAC, exhausting seats, and crashing the show. Rate limiting is the bouncer: it controls flow so the system stays healthy, fair, and predictable.\n\nRate limiting solves real problems:\n- Stop buggy clients or loops from taking down a service\n- Enforce fair usage across users (throttle noisy tenants)\n- Protect downstream systems (databases, external APIs)\n- Help enforce pricing tiers and quotas\n\n### An analogy: pipes, buckets, and turnstiles\n- Fixed-window: a turnstile that counts entries per minute and resets every minute.\n- Token bucket: a tap that refills tokens at steady rate; clients take tokens to pass. Allows bursts up to the token bucket size.\n- Leaky bucket: a bucket with a small hole — requests pour into it and leak out at fixed rate; excess spills over and is rejected.\n\n### How it works (flow)\n```mermaid\nflowchart TD\n  Client[Client Request] --> G[Gateway / API Layer]\n  G --> R{Rate Limiter}\n  R -->|Allowed| S[Service]\n  R -->|Throttled (429)| C[Reject/Queue]\n  S --> D[Downstream]\n```\n\n---\n\n## Common algorithms — short tour\n\n| Approach | Pros | Cons | When to Use |\n|----------|------|------|-------------|\n| Fixed Window | Simple, cheap | Burst at window edges; unfair around boundaries | Very low-cost infra, coarse limits (e.g., simple API keys) |\n| Sliding Window Log | Exact counting | Storage heavy (per-request entries) | Small scale or when strict enforcement needed |\n| Sliding Window Counter (approx) | Better boundary behavior, lower storage | Slight inaccuracy | General-purpose, good tradeoff |\n| Token Bucket | Allows bursts, easy to reason | Need atomic token ops in distributed setups | Rate-limited endpoints that need burst tolerance (uploads, interactive APIs) |\n| Leaky Bucket | Smooths bursts, predictable outflow | Rejects spikes quickly; less flexible for bursts | Traffic shaping where steady output is required |\n\n### Visual sequence (client perspective)\n```mermaid\nsequenceDiagram\n  Client->>Gateway: Request\n  Gateway->>RateLimiter: Check token/slot\n  alt allowed\n    RateLimiter-->>Gateway: OK (remaining=10)\n    Gateway->>Service: Forward request\n    Service-->>Gateway: 200 OK\n    Gateway-->>Client: 200 OK\n  else throttled\n    RateLimiter-->>Gateway: Throttle (Retry-After)\n    Gateway-->>Client: 429 Too Many Requests\n  end\n```\n\n---\n\n## BEFORE / AFTER: what rate limiting changes\n\n| Before | After |\n|--------|-------|\n| DB and downstream nodes overloaded by sudden spikes | Smoothing and capping spikes; downstream remains healthy |\n| A single misbehaving client can cause outage for others | Misbehaving client is throttled; others unaffected |\n| Unpredictable latency and costly autoscaling | More predictable latency and capacity planning |\n\n---\n\n## Practical implementations\n\n1. Single-process (in-memory) Token Bucket (fast, per-instance). Use for internal services behind a single gateway.\n2. Distributed via Redis (INCR with expiry or Lua script to manage tokens atomically). Good for multi-node gateways.\n3. API Gateway / Edge (NGINX, Envoy) built-in rate limiting — operate at the edge before traffic reaches app tier.\n4. Global quota systems — combine local throttles + central quota tokens (leaky bucket across regions).\n\nExample: simple token bucket behavior\n- Refill tokens at R tokens/sec\n- Bucket capacity = B tokens\n- On request: if tokens >= 1 -> consume and allow; else reject.\n\n### Simple in-process example (Python-like pseudo)\n```python\nimport time\n\nclass TokenBucket:\n    def __init__(self, rate, capacity):\n        self.rate = rate            # tokens per second\n        self.capacity = capacity    # max tokens\n        self.tokens = capacity\n        self.last = time.time()\n\n    def allow(self, cost=1):\n        now = time.time()\n        # add tokens since last check\n        self.tokens = min(self.capacity, self.tokens + (now - self.last) * self.rate)\n        self.last = now\n        if self.tokens >= cost:\n            self.tokens -= cost\n            return True\n        return False\n\nbucket = TokenBucket(rate=5, capacity=10)  # 5 req/s, burst up to 10\nif bucket.allow():\n    handle_request()\nelse:\n    return_429()\n```\n\nFor distributed systems, avoid naively calling INCR in multiple requests — use an atomic Lua script in Redis to implement token acquisition and consistent expiry.\n\n---\n\n## When to use which algorithm — practical rules\n- Use **fixed window** for very simple, non-critical limits (low infra cost).\n- Use **sliding window counter** when you need smoother boundaries without storing every request.\n- Use **token bucket** when you want to allow bursts but control long-term rate.\n- Use **leaky bucket** when you must smooth bursts into a constant output (traffic shaping).\n- Push limits to the **edge (CDN, API gateway)** where possible to block bad traffic early.\n\n---\n\n## Common pitfalls and how to avoid them\n- *Clock skew* — distributed systems using timestamps must consider clock drift. Prefer relative counters or centralized store with monotonic time.\n- *Underestimating storage* — sliding log stores per-request entries; use only for small scales.\n- *Over-throttling legitimate traffic* — provide sensible burst sizes and clear Retry-After headers, and consider grace for authenticated/paid users.\n- *Unfairness (IP sharing)* — per-IP rate limiting can penalize NATed users; prefer per-API-key / per-user where possible.\n- *Enforcement gaps* — make sure all ingress points (secondary gateways, internal APIs) apply limits consistently.\n- *DoS evasion* — attackers may rotate IPs or keys; combine rate limiting with heavier defenses (challenge/authorize).\n\n---\n\n## Implementation checklist\n- Choose dimensions: per-user, per-key, per-IP, global\n- Choose algorithm: token-bucket for burstiness, sliding-window for fairness\n- Decide enforcement point: edge vs app\n- Use atomic ops for distributed counters (Redis Lua scripts)\n- Return standard headers (429, Retry-After, X-RateLimit-Remaining, X-RateLimit-Reset)\n- Monitor: hits, throttles, rejected requests, latency impact\n- Test boundary conditions and time-window edges\n\n---\n\n## Quick example: Redis Lua token bucket sketch\n```text\n-- Pseudocode Lua script executed in Redis\n-- KEYS[1] = key, ARGV[1]=tokens_per_sec, ARGV[2]=capacity, ARGV[3]=now, ARGV[4]=cost\n-- load last state, compute new tokens based on delta, cap at capacity, if enough then subtract and save\n```\n\n(Use atomic Lua script to avoid race conditions when multiple gateway nodes check tokens simultaneously.)\n\n---\n\n## Final thoughts\nRate limiting is one of the most effective tools for predictable systems behavior. Choose a simple, well-understood algorithm and start at the edge. Tune burst capacity, give clients good feedback (429 + Retry-After), and instrument the system to iterate.\n\n",
    "keyTakeaways": [
      "Rate limiting prevents overload and enforces fairness — choose the algorithm that matches your burst and smoothing needs (token bucket for bursts, leaky bucket for smoothing).",
      "For distributed enforcement, use atomic ops (Redis Lua) or a centralized rate-limit service; push limits to the edge when possible.",
      "Watch out for clock skew, storage costs (sliding logs), per-IP unfairness, and provide clear client feedback (429 + Retry-After + headers)."
    ],
    "codeExample": "import time\n\nclass TokenBucket:\n    def __init__(self, rate, capacity):\n        self.rate = rate            # tokens per second\n        self.capacity = capacity    # max tokens\n        self.tokens = capacity\n        self.last = time.time()\n\n    def allow(self, cost=1):\n        now = time.time()\n        self.tokens = min(self.capacity, self.tokens + (now - self.last) * self.rate)\n        self.last = now\n        if self.tokens >= cost:\n            self.tokens -= cost\n            return True\n        return False\n\n# Usage\nbucket = TokenBucket(rate=5, capacity=10)  # 5 req/s, burst up to 10\nif bucket.allow():\n    # handle request\n    pass\nelse:\n    # return 429 Too Many Requests\n    pass",
    "furtherReading": [
      "https://nginx.org/en/docs/http/ngx_http_limit_req_module.html",
      "https://www.envoyproxy.io/docs/envoy/latest/intro/arch_overview/other_features/ratelimiting",
      "https://en.wikipedia.org/wiki/Token_bucket"
    ],
    "relatedTopics": [
      "API Gateway",
      "Backpressure"
    ]
  },
  "generatedAt": "2026-07-17T05:59:02.923Z"
}